rhash/__init__.py
rhash/rhash.py
rhash_Rhash-1.2.dist-info/LICENSE
rhash_Rhash-1.2.dist-info/METADATA
rhash_Rhash-1.2.dist-info/WHEEL
rhash_Rhash-1.2.dist-info/top_level.txt
rhash_Rhash-1.2.dist-info/RECORD
