Metadata-Version: 2.1
Name: rhash-Rhash
Version: 1.2
Summary: Python interface for librhash
Home-page: https://github.com/rhash/RHash
Author: Aleksey Kravchenko
Author-email: rhash.admin@gmail.com
License: BSD Zero Clause License
Project-URL: Source, https://github.com/rhash/RHash
Project-URL: Bug Tracker, https://github.com/rhash/RHash/issues
Classifier: Programming Language :: Python :: 3
Classifier: License :: OSI Approved :: BSD License
Classifier: Operating System :: OS Independent
Requires-Python: >=3.4
License-File: LICENSE
